{
  "id": "rec_8339c5c83dd5fc",
  "slug": "cazuela-de-guisantes-y-butifarra-negra",
  "titulo": "Cazuela De Guisantes Y Butifarra Negra",
  "resumen": "Limpia bien el puerro, pícalo y ponlo en una cazuelita con agua. Pela la zanahoria y los ajos, pícalos y añádelos. Pela 1 cebolleta, córtala por la mitad y agrega solo media. Reserva la otra mitad. Sazona y cuece el caldo durante unos 15 mi",
  "imagen_principal": "",
  "video_url": "",
  "tiempo_preparacion_min": 0,
  "tiempo_coccion_min": 0,
  "raciones": 4,
  "dificultad": "media",
  "categoria": "hortalizas",
  "tags": [
    "hortalizas",
    "arguinano",
    "cocina-espanola"
  ],
  "ingredientes": [
    {
      "cantidad": "600",
      "unidad": "g",
      "nombre": "guisantes desgranados (frescos)"
    },
    {
      "cantidad": "150",
      "unidad": "g",
      "nombre": "butifarra negra"
    },
    {
      "cantidad": "80",
      "unidad": "g",
      "nombre": "panceta curada"
    },
    {
      "cantidad": "3",
      "unidad": "",
      "nombre": "cebolletas"
    },
    {
      "cantidad": "1",
      "unidad": "",
      "nombre": "puerro"
    },
    {
      "cantidad": "1",
      "unidad": "",
      "nombre": "zanahoria"
    },
    {
      "cantidad": "2",
      "unidad": "dientes",
      "nombre": "ajo"
    },
    {
      "cantidad": "50",
      "unidad": "ml",
      "nombre": "vino blanco"
    },
    {
      "cantidad": "",
      "unidad": "",
      "nombre": "aceite de oliva virgen extra"
    },
    {
      "cantidad": "",
      "unidad": "",
      "nombre": "sal"
    }
  ],
  "pasos": [
    "Limpia bien el puerro, pícalo y ponlo en una cazuelita con agua. Pela la zanahoria y los ajos, pícalos y añádelos. Pela 1 cebolleta, córtala por la mitad y agrega solo media. Reserva la otra mitad. Sazona y cuece el caldo durante unos 15 minutos. Pela las otras dos cebolletas, y pícalas finamente junto con la media cebolleta reservada y ponlas a pochar en una tartera con un chorrito de aceite. Corta la panceta en daditos y añádelos. Corta la butifarra en rodajas y añádelas. Rehoga bien. Vierte el vino y dale un hervor. Incorpora los guisantes y cuela encima el caldo. Cocínalos durante 10 minutos. Sirve."
  ],
  "origen_url": "",
  "origen_nombre": "1000 recetas de oro - Karlos Arguinano (Planeta)",
  "autor": "Karlos Arguinano",
  "idioma": "es",
  "seo": {
    "meta_title": "Cazuela De Guisantes Y Butifarra Negra",
    "meta_description": "Limpia bien el puerro, pícalo y ponlo en una cazuelita con agua. Pela la zanahoria y los ajos, pícalos y añádelos. Pela 1 cebolleta, córtala por la mitad y agrega solo media. Reserva la otra mitad. Sazona y cuece el caldo durante unos 15 mi",
    "meta_keywords": "hortalizas, receta, cocina espanola"
  },
  "publicado": true,
  "created_at": "2026-05-15T00:00:00+00:00",
  "updated_at": "2026-05-15T00:00:00+00:00",
  "_createdAt": "2026-05-15T00:00:00+00:00",
  "_updatedAt": "2026-05-15T00:00:00+00:00",
  "_version": 1
}