{
  "id": "rec_8f0fd835163a47",
  "slug": "raya-con-setas-y-guisantes",
  "titulo": "Raya Con Setas Y Guisantes",
  "resumen": "Cuece los guisantes durante 10 minutos en una cazuelita con agua con sal. Resérvalos. Corta las cebolletas en dados y rehógalos en una tartera con un chorrito de aceite. Pela el tomate, córtalo en dados y añádelos. Sazona y saltea el conjun",
  "imagen_principal": "",
  "video_url": "",
  "tiempo_preparacion_min": 0,
  "tiempo_coccion_min": 0,
  "raciones": 4,
  "dificultad": "media",
  "categoria": "hortalizas",
  "tags": [
    "hortalizas",
    "arguinano",
    "cocina-espanola"
  ],
  "ingredientes": [
    {
      "cantidad": "600",
      "unidad": "g",
      "nombre": "raya"
    },
    {
      "cantidad": "200",
      "unidad": "g",
      "nombre": "setas de cultivo"
    },
    {
      "cantidad": "200",
      "unidad": "g",
      "nombre": "guisantes frescos (pelados)"
    },
    {
      "cantidad": "2",
      "unidad": "",
      "nombre": "cebolletas"
    },
    {
      "cantidad": "1",
      "unidad": "",
      "nombre": "tomate"
    },
    {
      "cantidad": "1",
      "unidad": "cucharada",
      "nombre": "harina"
    },
    {
      "cantidad": "200",
      "unidad": "ml",
      "nombre": "txakoli"
    },
    {
      "cantidad": "",
      "unidad": "",
      "nombre": "aceite de oliva virgen extra"
    },
    {
      "cantidad": "",
      "unidad": "",
      "nombre": "perejil"
    },
    {
      "cantidad": "",
      "unidad": "",
      "nombre": "sal"
    }
  ],
  "pasos": [
    "Cuece los guisantes durante 10 minutos en una cazuelita con agua con sal. Resérvalos. Corta las cebolletas en dados y rehógalos en una tartera con un chorrito de aceite. Pela el tomate, córtalo en dados y añádelos. Sazona y saltea el conjunto. Agrega la harina, rehógala y vierte el txakoli. Dale un hervor durante unos 3- 4 minutos. Limpia las setas, córtalas en tiras e incorpóralas. Añade un chorrito de agua, sazónalas y cocínalas durante 5 minutos. Limpia la raya, córtala en trozos grandes, sazónalos y agrégalos a la tartera. Incorpora los guisantes, tapa y cocina todo durante 3-4 minutos más. Espolvorea con un poco de perejil picado y sirve."
  ],
  "origen_url": "",
  "origen_nombre": "1000 recetas de oro - Karlos Arguinano (Planeta)",
  "autor": "Karlos Arguinano",
  "idioma": "es",
  "seo": {
    "meta_title": "Raya Con Setas Y Guisantes",
    "meta_description": "Cuece los guisantes durante 10 minutos en una cazuelita con agua con sal. Resérvalos. Corta las cebolletas en dados y rehógalos en una tartera con un chorrito de aceite. Pela el tomate, córtalo en dados y añádelos. Sazona y saltea el conjun",
    "meta_keywords": "hortalizas, receta, cocina espanola"
  },
  "publicado": true,
  "created_at": "2026-05-15T00:00:00+00:00",
  "updated_at": "2026-05-15T00:00:00+00:00",
  "_createdAt": "2026-05-15T00:00:00+00:00",
  "_updatedAt": "2026-05-15T00:00:00+00:00",
  "_version": 1
}