{
    "id": "prod_e5ba304e739c9371",
    "carta_id": "c_bde543072d79d538",
    "categoria_id": "cat_c3cf12f569565947",
    "local_id": "l_default",
    "nombre": "Croquetas",
    "descripcion": "",
    "precio": 7.5,
    "moneda": "EUR",
    "alergenos": [],
    "imagen_url": "",
    "imagen_mejorada_url": "",
    "es_especialidad": false,
    "texto_promocional": "",
    "ingredientes": [],
    "origen_import": "ocr",
    "disponible": true,
    "orden": 0,
    "created_at": "2026-05-12T10:32:07+00:00",
    "updated_at": "2026-05-12T10:32:07+00:00",
    "_updatedAt": "2026-05-12T10:32:07+00:00",
    "_version": 1,
    "_createdAt": "2026-05-12T10:32:07+00:00"
}